[
  {"id": 1, "userid": 1, "projectid": "1", "description": "Testing todo", "time": 4, "cost": 9},
  {"id": 2, "userid": 1, "projectid": "1", "description": "Testing another", "time": 6, "cost": 25},
  {"id": 3, "userid": 1, "projectid": "1", "description": "Something to do", "time": 1, "cost": 3},
  {"id": 4, "userid": 1, "projectid": "2", "description": "Testing todo", "time": 4, "cost": 9},
  {"id": 5, "userid": 1, "projectid": "2", "description": "Testing another", "time": 6, "cost": 25},
  {"id": 6, "userid": 1, "projectid": "2", "description": "Something to do", "time": 1, "cost": 3},
  {"id": 7, "userid": 1, "projectid": "3", "description": "Testing todo", "time": 4, "cost": 9},
  {"id": 8, "userid": 1, "projectid": "3", "description": "Testing another", "time": 6, "cost": 25},
  {"id": 9, "userid": 1, "projectid": "3", "description": "Something to do", "time": 1, "cost": 3},
  {"id": 10, "userid": 2, "projectid": "4", "description": "Testing todo", "time": 4, "cost": 9},
  {"id": 11, "userid": 2, "projectid": "4", "description": "Testing another", "time": 6, "cost": 25},
  {"id": 12, "userid": 2, "projectid": "4", "description": "Something to do", "time": 1, "cost": 3},
  {"id": 13, "userid": 2, "projectid": "5", "description": "Testing todo", "time": 4, "cost": 9},
  {"id": 14, "userid": 2, "projectid": "5", "description": "Testing another", "time": 6, "cost": 25},
  {"id": 15, "userid": 2, "projectid": "5", "description": "Something to do", "time": 1, "cost": 3}
]
